simplestyle/__init__.py
simplestyle/css.py
simplestyle/styles.py
simplestyle-1.2.0.dist-info/LICENSE.txt
simplestyle-1.2.0.dist-info/METADATA
simplestyle-1.2.0.dist-info/WHEEL
simplestyle-1.2.0.dist-info/top_level.txt
simplestyle-1.2.0.dist-info/RECORD
