Metadata-Version: 2.1
Name: simplestyle
Version: 1.2.0
Summary: Handling of simple stylesheets (subset of CSS)
Home-page: https://github.com/rotula/simplestyle
Author: Clemens Radl
Author-email: clemens.radl@googlemail.com
Maintainer: Clemens Radl
Maintainer-email: clemens.radl@googlemail.com
License: MIT
Keywords: CSS styles stylesheets
Platform: UNKNOWN
Classifier: License :: OSI Approved :: MIT License
Classifier: Development Status :: 5 - Production/Stable
Classifier: Programming Language :: Python
Classifier: Programming Language :: Python :: 2.7
Classifier: Programming Language :: Python :: 3.6
Classifier: Programming Language :: Python :: 3.7
Classifier: Programming Language :: Python :: 3.8
Classifier: Programming Language :: Python :: 3.9
Classifier: Intended Audience :: Developers
Classifier: Topic :: Text Processing :: Markup
License-File: LICENSE.txt
